{"about.md":"ce7a81c1","index.md":"ae406bfc","前端工程化_index.md":"2c834dfb","基础知识_01.html_基础.md":"d853debd","基础知识_01.html_搜索引擎优化-seo.md":"30f142f4","基础知识_02.css_index.md":"701bed13","基础知识_03.javascript_dom.md":"a8701080","基础知识_03.javascript_事件冒泡.md":"7f69438c","基础知识_04.代码规范_命名规范.md":"fbe9125d","基础知识_05.git_常用操作.md":"0362e8fd","基础知识_06.terminal_常用命令.md":"1e8523cf","基础知识_index.md":"e875d13e","百宝箱_index.md":"d1e5920c","百宝箱_工具集.md":"e03966cc","百宝箱_网站集.md":"105f8066","随笔_2015_刚开通的博客.md":"30d0388c","随笔_2015_用css3的transform来做一个立方体.md":"1885fdc8","随笔_2017_微信开发调试，常见问题解决.md":"233f3fe6","随笔_2018_a hook (orm) failed to load!.md":"e85ddf79","随笔_2018_cannot read property filecoverage of undefined....md":"b3380dda","随笔_2018_eslint 忽略部分提示.md":"09ccfd79","随笔_2018_failed to write coverage reports error error eexist file already exists mkdir....md":"62fc8fd8","随笔_2018_js数组去重方法.md":"6ffde0ef","随笔_2018_js获取对象键名.md":"9bd1940b","随笔_2018_windows10开启linux子系统.md":"4bd80b91","随笔_2018_canvas download时显示“网络错误”.md":"96adc4b3","随笔_2018_console.log中复制打印的对象.md":"f6866ac0","随笔_2018_vue中使用引入外部样式.md":"30aaa823","随笔_2018_【javascript数据结构】--栈.md":"e9e31033","随笔_2018_修改 hosts.md":"54dc7598","随笔_2018_微信小程序android真机下wx.previewimage黑屏.md":"0b381f3a","随笔_2018_微信小程序ios下禁用默认滚动事件.md":"3e0d1da0","随笔_2018_微信小程序ios端overflowauto滚动卡顿.md":"1991a430","随笔_2018_微信小程序“瀑布流”各种实现方式.md":"e90d9bac","随笔_2018_微信小程序上拉加载和下拉刷新（wepy）.md":"f03cb583","随笔_2018_微信小程序跳转无效.md":"1802a4a2","随笔_2018_矩阵乘积.md":"88ec2786","随笔_2018_解决微信小程序placeholder文字悬浮问题.md":"fe9da022","随笔_2018_设置窗口默认最大化、全屏(electron).md":"03781eed","随笔_2019_echart 配置项合并.md":"c5a4d28b","随笔_2019_eslint 自动格式化(vscode).md":"032f1321","随笔_2019_file ignored by default.  use a negated ignore pattern (like --ignore-pattern !) to override..md":"95ad1ead","随笔_2019_flutter 常用命令.md":"a26462d6","随笔_2019_macos 在终端打开 vscode.md":"5fc9e75a","随笔_2019_the process cannot access the file because it is being used by another process.md":"dd9fec7d","随笔_2019_windows10 下 vscode  remote-ssh 连接阿里云 ecs 云主机.md":"59b043ba","随笔_2019_asyncawait、promise 遍历.md":"839d741d","随笔_2019_nginx  php  https 配置.md":"3bcd4863","随笔_2019_个人博客搭建(hexo).md":"98ad6841","随笔_2019_利用 switch 语句进行范围判断(javascript).md":"4ac85315","随笔_2019_对象深拷贝(javascript).md":"4ac81ac1","随笔_2019_开发微信小程序环境配置(vscode).md":"82bebdd3","随笔_2019_扩展源码获取(chrome).md":"e22e0cf3","随笔_2019_日期获取的特殊情况(javascript).md":"fc8a074f","随笔_2019_正则表达式批量替换路径(vscode).md":"e9fc1f57","随笔_2019_苹果重置安全问题.md":"0f4cf261","随笔_2019_远程桌面共享多个显示屏(windows10).md":"5f44fdd4","随笔_2020_css文字两端对齐.md":"75ad768d","随笔_2020_cannot read property _wrapper of undefined.md":"edf9b361","随笔_2020_flutter 开发必备扩展(vscode).md":"5f6a6c4d","随笔_2020_html 中使用 svg 的不常见问题.md":"c5374b98","随笔_2020_javascript 中 label 的理解与应用.md":"6be83186","随笔_2020_javascript 实现重载(含 typescript ).md":"89039431","随笔_2020_nignx 处理异常操作流程.md":"25574fc8","随笔_2020_parsing error expression expected..md":"1d5a01f0","随笔_2020_the resource could not be loaded because the app transport security policy requires the use of a secure connection..md":"2ad21d96","随笔_2020_uncaught (in promise) undefined.md":"06c6619b","随笔_2020_vscode 搭建 java 开发环境.md":"c744f8f5","随笔_2020_vue 自定义事件传参.md":"525eb816","随笔_2020_wepy 格式化和语法高亮(vscode).md":"3181e649","随笔_2020_windows10 解决偶尔切换输入法无效.md":"d04468a6","随笔_2020_keep-alive include 加了 name 也无效.md":"87c5a05f","随笔_2020_webview 中获取微信发票抬头.md":"a7478cf5","随笔_2020_“there appears to be trouble with your network connection. retrying”.md":"a1717fe9","随笔_2020_【vs code】 常用快捷键.md":"431ab89b","随笔_2020_【vs code】编写我的第一个扩展.md":"d7eab41e","随笔_2020_修改 jar 包中 class 文件.md":"0e9c09aa","随笔_2020_修改 terminal 主机名和用户名显示.md":"d5486eae","随笔_2020_将数字转成 k结尾的字符串.md":"19d48b98","随笔_2020_工厂构造函数实现单例模式并传参.md":"6c0018ca","随笔_2020_微信内置浏览器中文竖排居中.md":"94c59152","随笔_2020_怎么监听页面某个 dom 元素被修改.md":"60b75a94","随笔_2020_文档对象模型（dom）.md":"3be1eb17","随笔_2020_正则匹配多行任意字符.md":"dd608f28","随笔_2020_比较好用的鼠标手势工具.md":"915af9ce","随笔_2020_让人抓狂的缩进冲突(eslint).md":"44b37a22","随笔_2021_centos7 - gyp err! build error.md":"5981866b","随笔_2021_gitlab 私有化管理 npm 包.md":"585528d8","随笔_2021_gitlab 自动化部署和局域网访问 gitlab pages.md":"ad14523e","随笔_2021_gitlab 跨版本升级.md":"23f982d4","随笔_2021_postman-请求加密和设置 cookie.md":"4acae74e","随笔_2021_promise 如何默认处理 catch.md":"3134b2b0","随笔_2021_axios 封装及 api 接口管理.md":"7b314166","随笔_2021_css 使用 calc() 无效的两种常见情况.md":"56251904","随笔_2021_ts 排除 node_modules 目录检测无效.md":"d09f6ed0","随笔_2021_【踩坑】使用自定义组件库引入 css 样式无效.md":"e83914da","随笔_2021_在 template 中使用 sass 变量.md":"51d6e00d","随笔_2021_小程序 - unexpected token var.md":"a5f6d1c6","随笔_2021_小程序 - 代码压缩实践.md":"a7313356","随笔_2021_小程序 - 画一个环形图( doughnut).md":"9202a0e9","随笔_2021_打造一个属于自己的“打卡”小程序.md":"9153a9a8","随笔_2021_纯 css 实现一些工作中常用效果.md":"ae4e3e82","随笔_2021_项目 nodejs 版本锁定及自动切换.md":"3a29bb2e","随笔_2022_01-科学计数转十进制.md":"4f27fd16","随笔_2022_02-chrome 日常使用五个必备小技巧.md":"10cc03a9","随笔_2022_ast 实战（ wepy 转 taro）.md":"c36e5c62","随笔_2022_semantic-release 自动发布.md":"4ab8a1fd","随笔_2022_vitepress 和 github pages 搭建个人博客.md":"1111cd3f","随笔_2022_【踩坑】异步下载 excel 文件打不开.md":"edff6879","面试题集_index.md":"da4f0cc1","面试题集_未分类_杂七杂八.md":"b1e1d548"}
